Metadata-Version: 1.1
Name: talons
Version: 0.2
Summary: Hooks for Falcon
Home-page: http://github.com/talons/talons
Author: Jay Pipes
Author-email: jaypipes@gmail.com
License: UNKNOWN
Keywords: falcon
Platform: UNKNOWN
Classifier: Intended Audience :: Information Technology
Classifier: Intended Audience :: Developers
Classifier: License :: OSI Approved :: Apache Software License
Classifier: Operating System :: POSIX :: Linux
Classifier: Programming Language :: Python
Classifier: Programming Language :: Python :: 2
Classifier: Programming Language :: Python :: 2.7
Classifier: Programming Language :: Python :: 2.6
Classifier: Programming Language :: Python :: 3.3
